{
    "title": "Penguin species prediction",
    "description": "Predict the species of penguins using measurements of the penguins, the goal is to build a model to classify each penguin correctly.",
    "mode": "guided",
    "model_metric": [
        "accuracy",
        0.95
    ],
    "data_size": 267,
    "missing_values": 0,
    "type": "object",
    "range": "Adelie Penguin (Pygoscelis adeliae)-Gentoo penguin (Pygoscelis papua)",
    "difficulty": [
        [
            "Data Cleaning",
            0
        ],
        [
            "Data Translation",
            0
        ],
        [
            "Data Transformation",
            0
        ],
        [
            "Statistics",
            0
        ],
        [
            "Model Training",
            0
        ],
        [
            "Predictive Modeling",
            0
        ]
    ],
    "dataset": "penguins_lter.csv",
    "subtasks": [
        {
            "title": "Data Cleaning",
            "status": "todo",
            "subtasks": [
                {
                    "status": "todo",
                    "action": [
                        "DataCleaning",
                        "Drop Column"
                    ],
                    "value": [
                        "Comments",
                        "Delta 15 N (o/oo)",
                        "Delta 13 C (o/oo)",
                        "Date Egg",
                        "Clutch Completion",
                        "Individual ID",
                        "Stage",
                        "Region",
                        "Sample Number",
                        "studyName"
                    ],
                    "title": "Drop Columns",
                    "description": "Remove columns that are irrelevant or redundant for the model.",
                    "hints": [
                        "Go to the Data Cleaning tab. Select the column(s), choose 'drop column', then click apply.",
                        "Drop the following column(s): Comments, Delta 15 N (o/oo), Delta 13 C (o/oo), Date Egg, Clutch Completion, Individual ID, Stage, Region, Sample Number, studyName."
                    ],
                    "applied_values": [],
                    "order": 1
                },
                {
                    "status": "todo",
                    "action": [
                        "DataCleaning",
                        "Remove-Missing"
                    ],
                    "value": [
                        "Sex"
                    ],
                    "title": "Remove Rows with Missing Values",
                    "description": "Remove rows that contain missing values in columns.",
                    "hints": [
                        "Go to the Data Cleaning tab. Select the column, choose 'remove missing', then click apply.",
                        "Remove rows with missing values in Sex."
                    ],
                    "applied_values": [],
                    "order": 1
                }
            ],
            "applied_values": [],
            "order": 2
        },
        {
            "title": "Data Translation",
            "status": "todo",
            "subtasks": [
                {
                    "status": "todo",
                    "action": [
                        "DataProcessing",
                        "OneHotEncoding"
                    ],
                    "value": [
                        "Sex",
                        "Island"
                    ],
                    "title": "One-Hot Encoding",
                    "description": "Convert categorical columns into one-hot encoded vectors.",
                    "hints": [
                        "Go to the Data Processing tab. Choose the column, select 'encoding', choose 'One Hot Encoding', then click apply.",
                        "Apply one-hot encoding to Sex, Island."
                    ],
                    "applied_values": [],
                    "order": 1
                }
            ],
            "applied_values": [],
            "order": 3
        },
        {
            "title": "Model Training",
            "status": "todo",
            "subtasks": [
                {
                    "status": "todo",
                    "action": [
                        "DataProcessing",
                        "AssignTarget"
                    ],
                    "value": [
                        "Species"
                    ],
                    "title": "Assign Target Variable",
                    "description": "Assign columns as the target variables for model training.",
                    "hints": [
                        "Go to the Data Processing tab. Choose the column, select 'Assign Target', then click apply.",
                        "Assign 'Species' as the target column."
                    ],
                    "applied_values": [],
                    "order": 1
                },
                {
                    "status": "todo",
                    "action": [
                        "DataProcessing",
                        "Split"
                    ],
                    "value": [
                        "20%"
                    ],
                    "title": "Train/Test Split",
                    "description": "Split dataset into training and testing sets.",
                    "hints": [
                        "Go to the Data Processing tab. Choose the column, assign the target, set the test ratio, then click split.",
                        "Use a test ratio of 20% for splitting the dataset."
                    ],
                    "applied_values": [],
                    "order": 2
                },
                {
                    "status": "todo",
                    "action": [
                        "ModelDevelopment",
                        "ParameterFinetuning"
                    ],
                    "value": [
                        [
                            "Random Forest",
                            105,
                            "entropy"
                        ]
                    ],
                    "title": "Parameter Finetuning",
                    "description": "Optimize model performance by modifying the parameters of the model.",
                    "hints": [
                        "Go to the Predictive Modeling tab. Select the model type, adjust parameters if needed, then click train.",
                        "Train the model using the following parameters: [['Random Forest', 105, 'entropy']]."
                    ],
                    "applied_values": [],
                    "order": 3
                }
            ],
            "applied_values": [],
            "order": 7
        },
        {
            "title": "Predictive Modeling",
            "status": "todo",
            "subtasks": [
                {
                    "status": "todo",
                    "action": [
                        "ModelDevelopment",
                        "ModelPerformance"
                    ],
                    "value": [
                        [
                            [
                                "Accuracy",
                                0.9850746268656716
                            ],
                            [
                                "Precision",
                                0.9865671641791044
                            ],
                            [
                                "Recall",
                                0.9850746268656716
                            ],
                            [
                                "data_size",
                                267
                            ],
                            [
                                "missing_values",
                                0
                            ],
                            [
                                "type",
                                "object"
                            ],
                            [
                                "range",
                                "Adelie Penguin (Pygoscelis adeliae)-Gentoo penguin (Pygoscelis papua)"
                            ]
                        ]
                    ],
                    "title": "Model Training",
                    "description": "Train a model and evaluate its performance.",
                    "hints": [],
                    "applied_values": [],
                    "order": 1
                }
            ],
            "applied_values": [],
            "order": null
        }
    ]
}